<?xml version='1.0' encoding='UTF-8'?>
<UserActionsWithDetails xmlns:ns0="http://schemas.datacontract.org/2004/07/Microsoft.Dynamics.Client.ServerForm.TaskRecording" xmlns:xsi="http://www.w3.org/2001/XMLSchema-instance"><UserAction Ref="i3"><Description>Go to Procurement and sourcing &gt; Purchase orders &gt; All purchase orders.</Description><NodeId>i3</NodeId><Sequence>21</Sequence><Navigation>mainmenu</Navigation><Navigation>ProcurementAndSourcing</Navigation><Navigation>PurchaseOrders</Navigation><ControlName>No Control Name</ControlName><ControlLabel /><ControlType /><Value /><CommandName /></UserAction><UserAction Ref="i6"><Description>Click New.</Description><NodeId>i6</NodeId><Sequence>21</Sequence><ControlName>SystemDefinedNewButton</ControlName><ControlLabel>New</ControlLabel><ControlType>CommandButton</ControlType><Value /><CommandName>Click</CommandName></UserAction><UserAction Ref="i9"><Description>In the Vendor account field, type a value.</Description><NodeId>i9</NodeId><Sequence>21</Sequence><ControlName>PurchTable_OrderAccount</ControlName><ControlLabel>Vendor account</ControlLabel><ControlType>Input</ControlType><Value>JMFE-33317</Value><CommandName /></UserAction><UserAction Ref="i12"><Description>Click Yes.</Description><NodeId>i12</NodeId><Sequence>21</Sequence><ControlName>Yes</ControlName><ControlLabel>Yes</ControlLabel><ControlType>CommandButton</ControlType><Value /><CommandName>Click</CommandName></UserAction><UserAction Ref="i14"><Description>In the Order type field, type a value.</Description><NodeId>i14</NodeId><Sequence>21</Sequence><ControlName>PurchTable_AVAOrderType</ControlName><ControlLabel>Order type</ControlLabel><ControlType>Input</ControlType><Value>STCKPO</Value><CommandName /></UserAction><UserAction Ref="i16"><Description>In the Site field, type a value.</Description><NodeId>i16</NodeId><Sequence>21</Sequence><ControlName>PurchTable_InventSiteId</ControlName><ControlLabel>Site</ControlLabel><ControlType>Input</ControlType><Value>JAXPDC</Value><CommandName /></UserAction><UserAction Ref="i18"><Description>In the Warehouse field, type a value.</Description><NodeId>i18</NodeId><Sequence>21</Sequence><ControlName>PurchTable_InventLocationId</ControlName><ControlLabel>Warehouse</ControlLabel><ControlType>Input</ControlType><Value>JAXPDC</Value><CommandName /></UserAction><UserAction Ref="i20"><Description>Click OK.</Description><NodeId>i20</NodeId><Sequence>21</Sequence><ControlName>OK</ControlName><ControlLabel>OK</ControlLabel><ControlType>CommandButton</ControlType><Value /><CommandName>Click</CommandName></UserAction><UserAction Ref="i22"><Description>On the Action Pane, click Purchase.</Description><NodeId>i22</NodeId><Sequence>21</Sequence><ControlName>Purchase</ControlName><ControlLabel>Purchase</ControlLabel><ControlType>AppBarTab</ControlType><Value /><CommandName>TabShown</CommandName></UserAction><UserAction Ref="i24"><Description>In the list, mark the selected row.</Description><NodeId>i24</NodeId><Sequence>21</Sequence><ControlName>LineSpec</ControlName><ControlLabel /><ControlType>Grid</ControlType><Value /><CommandName>MarkActiveRow</CommandName></UserAction><UserAction Ref="i26"><Description>In the Item number field, type a value.</Description><NodeId>i26</NodeId><Sequence>21</Sequence><ControlName>PurchLine_ItemId</ControlName><ControlLabel>Item number</ControlLabel><ControlType>Input</ControlType><Value>PT9083023120</Value><CommandName /></UserAction><UserAction Ref="i28"><Description>In the Quantity field, enter a number.</Description><NodeId>i28</NodeId><Sequence>21</Sequence><ControlName>PurchLine_PurchQtyGrid</ControlName><ControlLabel>Quantity</ControlLabel><ControlType>Real</ControlType><Value>5.00</Value><CommandName /></UserAction><UserAction Ref="i30"><Description>Click Save.</Description><NodeId>i30</NodeId><Sequence>21</Sequence><ControlName>SystemDefinedSaveButton</ControlName><ControlLabel>Save</ControlLabel><ControlType>CommandButton</ControlType><Value /><CommandName>Click</CommandName></UserAction><UserAction Ref="i32"><Description>Close the page.</Description><NodeId>i32</NodeId><Sequence>21</Sequence><ControlName>No Control Name</ControlName><ControlLabel /><ControlType /><Value /><CommandName>RequestClose</CommandName><Annotations /></UserAction><UserAction Ref="i34"><Description>Go to Procurement and sourcing &gt; Purchase orders &gt; Purchase order confirmation &gt; Confirm purchase orders.</Description><NodeId>i34</NodeId><Sequence>21</Sequence><Navigation>mainmenu</Navigation><Navigation>ProcurementAndSourcing</Navigation><Navigation>PurchaseOrders</Navigation><Navigation>PurchaseOrderConfirmation</Navigation><ControlName>No Control Name</ControlName><ControlLabel /><ControlType /><Value /><CommandName /></UserAction><UserAction Ref="i37"><Description>Click Add.</Description><NodeId>i37</NodeId><Sequence>21</Sequence><ControlName>AddParmTableButton</ControlName><ControlLabel>Add</ControlLabel><ControlType>CommandButton</ControlType><Value /><CommandName>Click</CommandName></UserAction><UserAction Ref="i39"><Description>In the list, mark the selected row.</Description><NodeId>i39</NodeId><Sequence>21</Sequence><ControlName>gridParmTable</ControlName><ControlLabel /><ControlType>Grid</ControlType><Value /><CommandName>MarkActiveRow</CommandName></UserAction><UserAction Ref="i41"><Description>In the Purchase order field, enter or select a value.</Description><NodeId>i41</NodeId><Sequence>21</Sequence><ControlName>PurchParmTable_PurchId</ControlName><ControlLabel>Purchase order</ControlLabel><ControlType>Input</ControlType><Value /><CommandName>RequestPopup</CommandName></UserAction><UserAction Ref="i44"><Description>Close the page.</Description><NodeId>i44</NodeId><Sequence>21</Sequence><ControlName>No Control Name</ControlName><ControlLabel /><ControlType /><Value /><CommandName>RequestClose</CommandName><Annotations><ns0:Annotation xsi:type="TaskGuideAnnotation">
                                <ns0:Description xsi:nil="true" />
                                <ns0:ExampleText xsi:nil="true" />
                                <ns0:GlobalId xsi:nil="true" />
                                <ns0:Hidden>true</ns0:Hidden>
                                <ns0:RecordingValueType>Preferred</ns0:RecordingValueType>
                                <ns0:Title xsi:nil="true" />
                              </ns0:Annotation>
                            </Annotations></UserAction><UserAction Ref="i46"><Description>In the Purchase order field, type a value.</Description><NodeId>i46</NodeId><Sequence>21</Sequence><ControlName>PurchParmTable_PurchId</ControlName><ControlLabel>Purchase order</ControlLabel><ControlType>Input</ControlType><Value>P0007930</Value><CommandName /></UserAction><UserAction Ref="i48"><Description>Click OK.</Description><NodeId>i48</NodeId><Sequence>21</Sequence><ControlName>OK</ControlName><ControlLabel>OK</ControlLabel><ControlType>CommandButton</ControlType><Value /><CommandName>Click</CommandName></UserAction></UserActionsWithDetails>